pyramid_sqlalchemy/__init__.py
pyramid_sqlalchemy/events.py
pyramid_sqlalchemy/fixtures.py
pyramid_sqlalchemy/meta.py
pyramid_sqlalchemy/model.py
pyramid_sqlalchemy/testing.py
pyramid_sqlalchemy/tests/__init__.py
pyramid_sqlalchemy/tests/test_init.py
pyramid_sqlalchemy/tests/test_testing.py
pyramid_sqlalchemy-1.6.dist-info/DESCRIPTION.rst
pyramid_sqlalchemy-1.6.dist-info/METADATA
pyramid_sqlalchemy-1.6.dist-info/RECORD
pyramid_sqlalchemy-1.6.dist-info/WHEEL
pyramid_sqlalchemy-1.6.dist-info/entry_points.txt
pyramid_sqlalchemy-1.6.dist-info/metadata.json
pyramid_sqlalchemy-1.6.dist-info/top_level.txt
pyramid_sqlalchemy-1.6.dist-info/zip-safe
