Metadata-Version: 2.0
Name: pyramid-sqlalchemy
Version: 1.6
Summary: SQLAlchemy integration for pyramid
Home-page: https://pyramid-sqlalchemy.readthedocs.org
Author: Wichert Akkerman
Author-email: wichert@wiggy.net
License: BSD
Platform: UNKNOWN
Classifier: Development Status :: 5 - Production/Stable
Classifier: Intended Audience :: Developers
Classifier: License :: OSI Approved :: BSD License
Classifier: Framework :: Pyramid
Classifier: Programming Language :: Python :: 2
Classifier: Programming Language :: Python :: 2.6
Classifier: Programming Language :: Python :: 2.7
Classifier: Programming Language :: Python :: 3
Classifier: Programming Language :: Python :: 3.4
Classifier: Programming Language :: Python :: 3.5
Classifier: Topic :: Database
Classifier: Topic :: Software Development :: Libraries :: Python Modules
Requires-Dist: SQLAlchemy (>=0.7.0)
Requires-Dist: zope.sqlalchemy (>=0.7.4)
Provides-Extra: docs
Requires-Dist: sphinx; extra == 'docs'
Provides-Extra: tests
Requires-Dist: pyramid; extra == 'tests'
